{
  "data": [
    {
      "agency": "US-ABC",
      "category": "<======== THIS IS MOCK DATA ================>",
      "category_explanation": null,
      "created_at": "2024-03-07T19:53:45.438381+00:00",
      "opportunity_assistance_listings": [
        {
          "assistance_listing_number": "56.681",
          "program_title": "Vasquez Inc"
        },
        {
          "assistance_listing_number": "56.864",
          "program_title": "Cox, Baker and Cruz"
        }
      ],
      "opportunity_id": 1,
      "opportunity_number": "ABC-1-XYZ-001",
      "opportunity_status": "forecasted",
      "opportunity_title": "<======== THIS IS MOCK DATA ================>",
      "summary": {
        "additional_info_url": "google.com",
        "additional_info_url_description": "Click me for additional info",
        "agency_code": "US-ABC",
        "agency_contact_description": "For more information contact us at - Name court treat father use particularly. You throw candidate play.",
        "agency_email_address": "jennifer39@example.net",
        "agency_email_address_description": "Contact US Alphabetical Basic Corp via email",
        "agency_name": "US Alphabetical Basic Corp",
        "agency_phone_number": "123-456-0000",
        "applicant_eligibility_description": "East statement travel cell car figure people. Must relationship room and artist wear. Focus almost report. Young down medical thing. Even computer magazine scientist deal. Particular message past commercial politics.",
        "applicant_types": ["state_governments", "county_governments"],
        "archive_date": "2024-04-03",
        "award_ceiling": 5210000,
        "award_floor": 2605000,
        "close_date": null,
        "close_date_description": null,
        "estimated_total_program_funding": 5210000,
        "expected_number_of_awards": 2,
        "fiscal_year": 2025,
        "forecasted_award_date": "2024-09-22",
        "forecasted_close_date": "2024-05-21",
        "forecasted_close_date_description": "Current least organization thought herself.",
        "forecasted_post_date": "2024-03-26",
        "forecasted_project_start_date": "2025-02-16",
        "funding_categories": ["recovery_act"],
        "funding_category_description": null,
        "funding_instruments": ["grant", "cooperative_agreement"],
        "is_cost_sharing": true,
        "is_forecast": true,
        "post_date": "2024-03-06",
        "summary_description": "Example summary - Toward fall article this behind ago skin. Song read hundred each carry science during call.",
        "version_number": 1
      },
      "updated_at": "2024-03-07T19:53:45.438381+00:00"
    },
    {
      "agency": "US-XYZ",
      "category": "discretionary",
      "category_explanation": null,
      "created_at": "2024-03-07T19:53:45.546152+00:00",
      "opportunity_assistance_listings": [
        {
          "assistance_listing_number": "96.788",
          "program_title": "Davis-Quinn"
        },
        {
          "assistance_listing_number": "84.212",
          "program_title": "Hall, Reid and Allen"
        }
      ],
      "opportunity_id": 2,
      "opportunity_number": "ABC-2-XYZ-001",
      "opportunity_status": "forecasted",
      "opportunity_title": "Research into Therapist, speech and language industry",
      "summary": {
        "additional_info_url": "grants.gov",
        "additional_info_url_description": "Click me for additional info",
        "agency_code": "US-XYZ",
        "agency_contact_description": "For more information contact us at - Design experience I whom. National night lawyer keep.",
        "agency_email_address": "william03@example.com",
        "agency_email_address_description": "Contact US Xylophone Yak Zoo via email",
        "agency_name": "US Xylophone Yak Zoo",
        "agency_phone_number": "123-456-0001",
        "applicant_eligibility_description": "Medical dream although test service. Expect knowledge that thing. Idea at size television source not cold. Away list decide turn. Purpose kid leave. Order exist glass base out.",
        "applicant_types": [
          "city_or_township_governments",
          "independent_school_districts",
          "special_district_governments"
        ],
        "archive_date": "2024-04-03",
        "award_ceiling": 7320000,
        "award_floor": 7320000,
        "close_date": null,
        "close_date_description": null,
        "estimated_total_program_funding": 7320000,
        "expected_number_of_awards": 1,
        "fiscal_year": 2024,
        "forecasted_award_date": "2024-09-16",
        "forecasted_close_date": "2024-05-27",
        "forecasted_close_date_description": "Happen born space.",
        "forecasted_post_date": "2024-03-23",
        "forecasted_project_start_date": "2024-10-10",
        "funding_categories": ["agriculture"],
        "funding_category_description": null,
        "funding_instruments": [
          "procurement_contract",
          "other",
          "cooperative_agreement"
        ],
        "is_cost_sharing": false,
        "is_forecast": true,
        "post_date": "2024-03-06",
        "summary_description": "Example summary - Grow set indicate bag blood they. Later beyond consider discover another write.",
        "version_number": 1
      },
      "updated_at": "2024-03-07T19:53:45.546152+00:00"
    },
    {
      "agency": "US-123",
      "category": "discretionary",
      "category_explanation": null,
      "created_at": "2024-03-07T19:53:45.605974+00:00",
      "opportunity_assistance_listings": [
        {
          "assistance_listing_number": "58.278",
          "program_title": "Barr, Fernandez and Mills"
        },
        {
          "assistance_listing_number": "23.510",
          "program_title": "Malone, Delacruz and Macdonald"
        },
        {
          "assistance_listing_number": "63.507",
          "program_title": "Davis, Cross and Patrick"
        }
      ],
      "opportunity_id": 3,
      "opportunity_number": "ABC-3-XYZ-001",
      "opportunity_status": "forecasted",
      "opportunity_title": "Research into Building control surveyor industry",
      "summary": {
        "additional_info_url": "google.com",
        "additional_info_url_description": "Click me for additional info",
        "agency_code": "US-123",
        "agency_contact_description": "For more information contact us at - Region appear operation material. Box sort fast quality teach protect. View keep bag society help rise.",
        "agency_email_address": "yanderson@example.com",
        "agency_email_address_description": "Contact US Number Department via email",
        "agency_name": "US Number Department",
        "agency_phone_number": "123-456-0002",
        "applicant_eligibility_description": null,
        "applicant_types": [
          "public_and_state_institutions_of_higher_education",
          "private_institutions_of_higher_education",
          "federally_recognized_native_american_tribal_governments"
        ],
        "archive_date": "2024-04-03",
        "award_ceiling": 370000,
        "award_floor": 21764,
        "close_date": null,
        "close_date_description": null,
        "estimated_total_program_funding": 370000,
        "expected_number_of_awards": 17,
        "fiscal_year": 2025,
        "forecasted_award_date": "2024-09-30",
        "forecasted_close_date": "2024-05-02",
        "forecasted_close_date_description": "Those strategy will.",
        "forecasted_post_date": "2024-03-27",
        "forecasted_project_start_date": "2025-02-13",
        "funding_categories": ["arts"],
        "funding_category_description": null,
        "funding_instruments": ["procurement_contract", "grant", "other"],
        "is_cost_sharing": false,
        "is_forecast": true,
        "post_date": "2024-02-17",
        "summary_description": "Example summary - Seem participant appear window policy. General talk spend white most pull rule fight. Pm west benefit station like party. Moment meet star.",
        "version_number": 1
      },
      "updated_at": "2024-03-07T19:53:45.605974+00:00"
    },
    {
      "agency": "US-ABC",
      "category": "continuation",
      "category_explanation": null,
      "created_at": "2024-03-07T19:53:45.655857+00:00",
      "opportunity_assistance_listings": [
        {
          "assistance_listing_number": "49.905",
          "program_title": "Ward-Brady"
        },
        {
          "assistance_listing_number": "04.911",
          "program_title": "Neal, Taylor and Wallace"
        },
        {
          "assistance_listing_number": "54.642",
          "program_title": "Wolfe LLC"
        }
      ],
      "opportunity_id": 4,
      "opportunity_number": "ABC-4-XYZ-001",
      "opportunity_status": "forecasted",
      "opportunity_title": "Research into Restaurant manager industry",
      "summary": {
        "additional_info_url": "grants.gov",
        "additional_info_url_description": "Click me for additional info",
        "agency_code": "US-ABC",
        "agency_contact_description": "For more information contact us at - Hard so road practice rate him. Type surface player beautiful. Player dark provide whose.",
        "agency_email_address": "cbest@example.net",
        "agency_email_address_description": "Contact US Alphabetical Basic Corp via email",
        "agency_name": "US Alphabetical Basic Corp",
        "agency_phone_number": "123-456-0003",
        "applicant_eligibility_description": null,
        "applicant_types": ["other_native_american_tribal_organizations"],
        "archive_date": "2024-03-30",
        "award_ceiling": 5850000,
        "award_floor": 417857,
        "close_date": null,
        "close_date_description": null,
        "estimated_total_program_funding": 5850000,
        "expected_number_of_awards": 14,
        "fiscal_year": 2025,
        "forecasted_award_date": "2024-09-10",
        "forecasted_close_date": "2024-05-14",
        "forecasted_close_date_description": "Teach game economy newspaper western although.",
        "forecasted_post_date": "2024-03-25",
        "forecasted_project_start_date": "2025-01-31",
        "funding_categories": [
          "consumer_protection",
          "business_and_commerce",
          "community_development"
        ],
        "funding_category_description": "Goal place friend risk suddenly.",
        "funding_instruments": ["grant", "cooperative_agreement"],
        "is_cost_sharing": false,
        "is_forecast": true,
        "post_date": "2024-02-21",
        "summary_description": "Example summary - Seven tough western business investment. Show raise production pass.",
        "version_number": 1
      },
      "updated_at": "2024-03-07T19:53:45.655857+00:00"
    },
    {
      "agency": "US-XYZ",
      "category": "earmark",
      "category_explanation": null,
      "created_at": "2024-03-07T19:53:45.700646+00:00",
      "opportunity_assistance_listings": [
        {
          "assistance_listing_number": "95.860",
          "program_title": "Scott LLC"
        }
      ],
      "opportunity_id": 5,
      "opportunity_number": "ABC-5-XYZ-001",
      "opportunity_status": "forecasted",
      "opportunity_title": "Research into Therapist, speech and language industry",
      "summary": {
        "additional_info_url": "google.com",
        "additional_info_url_description": "Click me for additional info",
        "agency_code": "US-XYZ",
        "agency_contact_description": "For more information contact us at - Figure chair glass need significant focus section. Agent goal bad would consider.",
        "agency_email_address": "rileynatalie@example.org",
        "agency_email_address_description": "Contact US Xylophone Yak Zoo via email",
        "agency_name": "US Xylophone Yak Zoo",
        "agency_phone_number": "123-456-0004",
        "applicant_eligibility_description": "Authority second far rise somebody himself voice. End indicate everybody term agreement treat doctor sure. Life very let nor open sort area. Maybe station here win change Republican.",
        "applicant_types": [
          "nonprofits_non_higher_education_with_501c3",
          "nonprofits_non_higher_education_without_501c3",
          "public_and_indian_housing_authorities"
        ],
        "archive_date": "2024-03-28",
        "award_ceiling": 4405000,
        "award_floor": 1468333,
        "close_date": null,
        "close_date_description": null,
        "estimated_total_program_funding": 4405000,
        "expected_number_of_awards": 3,
        "fiscal_year": 2024,
        "forecasted_award_date": "2024-09-09",
        "forecasted_close_date": "2024-05-06",
        "forecasted_close_date_description": "Property ball forward people.",
        "forecasted_post_date": "2024-03-26",
        "forecasted_project_start_date": "2024-11-13",
        "funding_categories": ["disaster_prevention_and_relief"],
        "funding_category_description": "Resource education change.",
        "funding_instruments": ["procurement_contract"],
        "is_cost_sharing": false,
        "is_forecast": true,
        "post_date": "2024-03-04",
        "summary_description": "Example summary - Talk road today red work majority result born. Paper guy financial never town house effort. Vote enter close pay car item.",
        "version_number": 1
      },
      "updated_at": "2024-03-07T19:53:45.700646+00:00"
    },
    {
      "agency": "US-123",
      "category": "other",
      "category_explanation": "Category as chosen by order #35",
      "created_at": "2024-03-07T19:53:45.826839+00:00",
      "opportunity_assistance_listings": [
        {
          "assistance_listing_number": "84.592",
          "program_title": "Swanson-Armstrong"
        },
        {
          "assistance_listing_number": "14.690",
          "program_title": "Myers-Macias"
        },
        {
          "assistance_listing_number": "28.011",
          "program_title": "Lopez, Watson and Palmer"
        }
      ],
      "opportunity_id": 6,
      "opportunity_number": "ABC-6-XYZ-001",
      "opportunity_status": "posted",
      "opportunity_title": "Research into Armed forces operational officer industry",
      "summary": {
        "additional_info_url": "grants.gov",
        "additional_info_url_description": "Click me for additional info",
        "agency_code": "US-123",
        "agency_contact_description": "For more information contact us at - Create since ahead. Firm relate tax agreement there last.",
        "agency_email_address": "leethomas@example.net",
        "agency_email_address_description": "Contact US Number Department via email",
        "agency_name": "US Number Department",
        "agency_phone_number": "123-456-0005",
        "applicant_eligibility_description": null,
        "applicant_types": ["individuals"],
        "archive_date": "2024-03-29",
        "award_ceiling": 1485000,
        "award_floor": 247500,
        "close_date": "2024-03-26",
        "close_date_description": "Our support ball laugh maintain professor.",
        "estimated_total_program_funding": 1485000,
        "expected_number_of_awards": 6,
        "fiscal_year": null,
        "forecasted_award_date": null,
        "forecasted_close_date": null,
        "forecasted_close_date_description": null,
        "forecasted_post_date": null,
        "forecasted_project_start_date": null,
        "funding_categories": [
          "education",
          "energy",
          "employment_labor_and_training"
        ],
        "funding_category_description": "Better him threat.",
        "funding_instruments": ["other"],
        "is_cost_sharing": false,
        "is_forecast": false,
        "post_date": "2024-03-04",
        "summary_description": "Example summary - Radio recognize nothing hospital role rich away.",
        "version_number": 1
      },
      "updated_at": "2024-03-07T19:53:45.826839+00:00"
    },
    {
      "agency": "US-ABC",
      "category": "discretionary",
      "category_explanation": null,
      "created_at": "2024-03-07T19:53:45.912573+00:00",
      "opportunity_assistance_listings": [
        {
          "assistance_listing_number": "47.309",
          "program_title": "Adkins-Hale"
        }
      ],
      "opportunity_id": 7,
      "opportunity_number": "ABC-7-XYZ-001",
      "opportunity_status": "posted",
      "opportunity_title": "Research into Scientist, forensic industry",
      "summary": {
        "additional_info_url": "google.com",
        "additional_info_url_description": "Click me for additional info",
        "agency_code": "US-ABC",
        "agency_contact_description": "For more information contact us at - Anything office near area. Leader rather section article truth American.",
        "agency_email_address": "michael30@example.org",
        "agency_email_address_description": "Contact US Alphabetical Basic Corp via email",
        "agency_name": "US Alphabetical Basic Corp",
        "agency_phone_number": "123-456-0006",
        "applicant_eligibility_description": "Expert full economic. Case move always billion growth heart keep. Nearly space hour blood. Somebody class high argue reflect pressure set. White source real.",
        "applicant_types": [
          "small_businesses",
          "other",
          "for_profit_organizations_other_than_small_businesses"
        ],
        "archive_date": "2024-04-02",
        "award_ceiling": 8560000,
        "award_floor": 389090,
        "close_date": "2024-03-24",
        "close_date_description": "Catch memory top offer stay.",
        "estimated_total_program_funding": 8560000,
        "expected_number_of_awards": 22,
        "fiscal_year": null,
        "forecasted_award_date": null,
        "forecasted_close_date": null,
        "forecasted_close_date_description": null,
        "forecasted_post_date": null,
        "forecasted_project_start_date": null,
        "funding_categories": ["food_and_nutrition", "environment"],
        "funding_category_description": null,
        "funding_instruments": ["grant", "cooperative_agreement"],
        "is_cost_sharing": true,
        "is_forecast": false,
        "post_date": "2024-02-26",
        "summary_description": "Example summary - Strong focus wide. Grow meeting operation book among. Determine effect politics hard look.",
        "version_number": 1
      },
      "updated_at": "2024-03-07T19:53:45.912573+00:00"
    },
    {
      "agency": "US-XYZ",
      "category": "continuation",
      "category_explanation": null,
      "created_at": "2024-03-07T19:53:45.996655+00:00",
      "opportunity_assistance_listings": [
        {
          "assistance_listing_number": "15.059",
          "program_title": "Chavez, Thompson and Davis"
        }
      ],
      "opportunity_id": 8,
      "opportunity_number": "ABC-8-XYZ-001",
      "opportunity_status": "posted",
      "opportunity_title": "Research into Risk analyst industry",
      "summary": {
        "additional_info_url": "grants.gov",
        "additional_info_url_description": "Click me for additional info",
        "agency_code": "US-XYZ",
        "agency_contact_description": "For more information contact us at - Trade whose language three must. Hold get though. Wind value strong phone maintain.",
        "agency_email_address": "ipope@example.com",
        "agency_email_address_description": "Contact US Xylophone Yak Zoo via email",
        "agency_name": "US Xylophone Yak Zoo",
        "agency_phone_number": "123-456-0007",
        "applicant_eligibility_description": "Follow probably simple threat. Like image new according like. Tv law on light fight. In successful even sometimes. Program toward child institution. Paper open their lot season treat quickly.",
        "applicant_types": ["state_governments", "unrestricted"],
        "archive_date": "2024-03-29",
        "award_ceiling": 7640000,
        "award_floor": 955000,
        "close_date": "2024-03-24",
        "close_date_description": "Happy every middle drop now detail.",
        "estimated_total_program_funding": 7640000,
        "expected_number_of_awards": 8,
        "fiscal_year": null,
        "forecasted_award_date": null,
        "forecasted_close_date": null,
        "forecasted_close_date_description": null,
        "forecasted_post_date": null,
        "forecasted_project_start_date": null,
        "funding_categories": ["health", "housing"],
        "funding_category_description": "Tend there friend open.",
        "funding_instruments": ["procurement_contract"],
        "is_cost_sharing": false,
        "is_forecast": false,
        "post_date": "2024-02-20",
        "summary_description": "Example summary - Share lead always part charge wait. Of price majority mission development particularly because. Carry radio pattern leader apply. Sell manager audience rule.",
        "version_number": 1
      },
      "updated_at": "2024-03-07T19:53:45.996655+00:00"
    },
    {
      "agency": "US-123",
      "category": "discretionary",
      "category_explanation": null,
      "created_at": "2024-03-07T19:53:46.057708+00:00",
      "opportunity_assistance_listings": [
        {
          "assistance_listing_number": "04.706",
          "program_title": "Wilson Group"
        }
      ],
      "opportunity_id": 9,
      "opportunity_number": "ABC-9-XYZ-001",
      "opportunity_status": "posted",
      "opportunity_title": "Research into Environmental health practitioner industry",
      "summary": {
        "additional_info_url": "google.com",
        "additional_info_url_description": "Click me for additional info",
        "agency_code": "US-123",
        "agency_contact_description": "For more information contact us at - Rock number key. Thought better nor month gas wife. Million our happy start ahead. Need leg physical very question.",
        "agency_email_address": "xavery@example.com",
        "agency_email_address_description": "Contact US Number Department via email",
        "agency_name": "US Number Department",
        "agency_phone_number": "123-456-0008",
        "applicant_eligibility_description": "Change as way second everyone. Not him as member actually line attack. Usually Mrs easy character local. Finally book suddenly address home discover attention fast.",
        "applicant_types": ["county_governments"],
        "archive_date": "2024-04-02",
        "award_ceiling": 4530000,
        "award_floor": 1510000,
        "close_date": "2024-03-26",
        "close_date_description": "Present relate job reduce little industry.",
        "estimated_total_program_funding": 4530000,
        "expected_number_of_awards": 3,
        "fiscal_year": null,
        "forecasted_award_date": null,
        "forecasted_close_date": null,
        "forecasted_close_date_description": null,
        "forecasted_post_date": null,
        "forecasted_project_start_date": null,
        "funding_categories": ["humanities"],
        "funding_category_description": "Section everything think music hundred.",
        "funding_instruments": ["grant", "other", "cooperative_agreement"],
        "is_cost_sharing": true,
        "is_forecast": false,
        "post_date": "2024-02-16",
        "summary_description": "Example summary - Any total collection pull morning. Dream minute various. Open child today probably husband.",
        "version_number": 1
      },
      "updated_at": "2024-03-07T19:53:46.057708+00:00"
    },
    {
      "agency": "US-ABC",
      "category": "earmark",
      "category_explanation": null,
      "created_at": "2024-03-07T19:53:46.129512+00:00",
      "opportunity_assistance_listings": [
        {
          "assistance_listing_number": "64.332",
          "program_title": "Hodge, Hunter and Bush"
        },
        {
          "assistance_listing_number": "35.531",
          "program_title": "Stout-Smith"
        }
      ],
      "opportunity_id": 10,
      "opportunity_number": "ABC-10-XYZ-001",
      "opportunity_status": "posted",
      "opportunity_title": "Research into Fine artist industry",
      "summary": {
        "additional_info_url": "grants.gov",
        "additional_info_url_description": "Click me for additional info",
        "agency_code": "US-ABC",
        "agency_contact_description": "For more information contact us at - Drug right toward hard people interest real. Any big provide sure involve conference style.",
        "agency_email_address": "shannonstewart@example.com",
        "agency_email_address_description": "Contact US Alphabetical Basic Corp via email",
        "agency_name": "US Alphabetical Basic Corp",
        "agency_phone_number": "123-456-0009",
        "applicant_eligibility_description": "Clearly economy final at heavy. Anyone everything agent reflect. Trouble action clearly garden. Able one sit production there course minute.",
        "applicant_types": [
          "city_or_township_governments",
          "special_district_governments"
        ],
        "archive_date": "2024-03-31",
        "award_ceiling": 9995000,
        "award_floor": 624687,
        "close_date": "2024-03-25",
        "close_date_description": "Weight want one coach.",
        "estimated_total_program_funding": 9995000,
        "expected_number_of_awards": 16,
        "fiscal_year": null,
        "forecasted_award_date": null,
        "forecasted_close_date": null,
        "forecasted_close_date_description": null,
        "forecasted_post_date": null,
        "forecasted_project_start_date": null,
        "funding_categories": [
          "income_security_and_social_services",
          "infrastructure_investment_and_jobs_act",
          "information_and_statistics"
        ],
        "funding_category_description": null,
        "funding_instruments": ["procurement_contract", "other"],
        "is_cost_sharing": false,
        "is_forecast": false,
        "post_date": "2024-03-02",
        "summary_description": "Example summary - Work federal hospital participant her occur something claim.",
        "version_number": 1
      },
      "updated_at": "2024-03-07T19:53:46.129512+00:00"
    },
    {
      "agency": "US-XYZ",
      "category": "other",
      "category_explanation": "Category as chosen by order #120",
      "created_at": "2024-03-07T19:53:46.229062+00:00",
      "opportunity_assistance_listings": [
        {
          "assistance_listing_number": "56.833",
          "program_title": "Simpson Group"
        },
        {
          "assistance_listing_number": "39.675",
          "program_title": "Osborne, Arellano and Hensley"
        },
        {
          "assistance_listing_number": "23.716",
          "program_title": "Williams, Rivera and Wood"
        }
      ],
      "opportunity_id": 11,
      "opportunity_number": "ABC-11-XYZ-001",
      "opportunity_status": "closed",
      "opportunity_title": "Research into Clinical biochemist industry",
      "summary": {
        "additional_info_url": "google.com",
        "additional_info_url_description": "Click me for additional info",
        "agency_code": "US-XYZ",
        "agency_contact_description": "For more information contact us at - Scientist real half fire risk claim. Among suffer thus nature way.",
        "agency_email_address": "hgillespie@example.com",
        "agency_email_address_description": "Contact US Xylophone Yak Zoo via email",
        "agency_name": "US Xylophone Yak Zoo",
        "agency_phone_number": "123-456-0010",
        "applicant_eligibility_description": "Town level method various court. Nature themselves piece offer current. My some work surface rate. American laugh would although walk. Wide political short maybe art safe computer.",
        "applicant_types": [
          "public_and_state_institutions_of_higher_education",
          "private_institutions_of_higher_education",
          "independent_school_districts"
        ],
        "archive_date": "2024-03-31",
        "award_ceiling": 3975000,
        "award_floor": 496875,
        "close_date": "2024-02-21",
        "close_date_description": "Low employee argue performance majority degree occur.",
        "estimated_total_program_funding": 3975000,
        "expected_number_of_awards": 8,
        "fiscal_year": null,
        "forecasted_award_date": null,
        "forecasted_close_date": null,
        "forecasted_close_date_description": null,
        "forecasted_post_date": null,
        "forecasted_project_start_date": null,
        "funding_categories": [
          "law_justice_and_legal_services",
          "natural_resources"
        ],
        "funding_category_description": "Traditional shoulder success may hard.",
        "funding_instruments": ["cooperative_agreement"],
        "is_cost_sharing": true,
        "is_forecast": false,
        "post_date": "2024-01-25",
        "summary_description": "Example summary - Nice discuss test employee guess. Camera fund only.",
        "version_number": 1
      },
      "updated_at": "2024-03-07T19:53:46.229062+00:00"
    },
    {
      "agency": "US-123",
      "category": "earmark",
      "category_explanation": null,
      "created_at": "2024-03-07T19:53:46.317103+00:00",
      "opportunity_assistance_listings": [
        {
          "assistance_listing_number": "94.859",
          "program_title": "Miller, Martin and Riggs"
        },
        {
          "assistance_listing_number": "76.541",
          "program_title": "Joyce Inc"
        }
      ],
      "opportunity_id": 12,
      "opportunity_number": "ABC-12-XYZ-001",
      "opportunity_status": "closed",
      "opportunity_title": "Research into Medical sales representative industry",
      "summary": {
        "additional_info_url": "grants.gov",
        "additional_info_url_description": "Click me for additional info",
        "agency_code": "US-123",
        "agency_contact_description": "For more information contact us at - Film until stuff. Oil story ago feeling could remember see. Operation check eat nation scientist go. Quality challenge manage art former vote focus.",
        "agency_email_address": "richardmiller@example.net",
        "agency_email_address_description": "Contact US Number Department via email",
        "agency_name": "US Number Department",
        "agency_phone_number": "123-456-0011",
        "applicant_eligibility_description": null,
        "applicant_types": [
          "other_native_american_tribal_organizations",
          "federally_recognized_native_american_tribal_governments",
          "public_and_indian_housing_authorities"
        ],
        "archive_date": "2024-03-29",
        "award_ceiling": 495000,
        "award_floor": 99000,
        "close_date": "2024-02-20",
        "close_date_description": "Over knowledge use board because table short.",
        "estimated_total_program_funding": 495000,
        "expected_number_of_awards": 5,
        "fiscal_year": null,
        "forecasted_award_date": null,
        "forecasted_close_date": null,
        "forecasted_close_date_description": null,
        "forecasted_post_date": null,
        "forecasted_project_start_date": null,
        "funding_categories": [
          "opportunity_zone_benefits",
          "science_technology_and_other_research_and_development",
          "regional_development"
        ],
        "funding_category_description": null,
        "funding_instruments": ["grant"],
        "is_cost_sharing": false,
        "is_forecast": false,
        "post_date": "2024-01-31",
        "summary_description": "Example summary - As now center race information. Pretty wrong I.",
        "version_number": 1
      },
      "updated_at": "2024-03-07T19:53:46.317103+00:00"
    },
    {
      "agency": "US-ABC",
      "category": "discretionary",
      "category_explanation": null,
      "created_at": "2024-03-07T19:53:46.404970+00:00",
      "opportunity_assistance_listings": [
        {
          "assistance_listing_number": "62.834",
          "program_title": "Brown, Delgado and Wheeler"
        },
        {
          "assistance_listing_number": "19.873",
          "program_title": "West Ltd"
        },
        {
          "assistance_listing_number": "23.890",
          "program_title": "Fisher-Graham"
        }
      ],
      "opportunity_id": 13,
      "opportunity_number": "ABC-13-XYZ-001",
      "opportunity_status": "closed",
      "opportunity_title": "Research into Fine artist industry",
      "summary": {
        "additional_info_url": "google.com",
        "additional_info_url_description": "Click me for additional info",
        "agency_code": "US-ABC",
        "agency_contact_description": "For more information contact us at - Popular them strategy person spend fall claim. Positive than Congress imagine. Second indeed son least side as.",
        "agency_email_address": "ashleyjuarez@example.com",
        "agency_email_address_description": "Contact US Alphabetical Basic Corp via email",
        "agency_name": "US Alphabetical Basic Corp",
        "agency_phone_number": "123-456-0012",
        "applicant_eligibility_description": "Foreign recently expert peace middle executive those clear. Those economy painting wish. Economic name between war list stay fund. Chair laugh study feeling federal entire ready. Social energy executive create.",
        "applicant_types": [
          "nonprofits_non_higher_education_with_501c3",
          "nonprofits_non_higher_education_without_501c3"
        ],
        "archive_date": "2024-03-31",
        "award_ceiling": 9990000,
        "award_floor": 2497500,
        "close_date": "2024-02-27",
        "close_date_description": "Environment wall factor control thank.",
        "estimated_total_program_funding": 9990000,
        "expected_number_of_awards": 4,
        "fiscal_year": null,
        "forecasted_award_date": null,
        "forecasted_close_date": null,
        "forecasted_close_date_description": null,
        "forecasted_post_date": null,
        "forecasted_project_start_date": null,
        "funding_categories": ["transportation"],
        "funding_category_description": "Energy call far hit recognize TV standard return.",
        "funding_instruments": [
          "procurement_contract",
          "other",
          "cooperative_agreement"
        ],
        "is_cost_sharing": false,
        "is_forecast": false,
        "post_date": "2024-01-25",
        "summary_description": "Example summary - Skin true quickly professional company. Foreign off difficult.",
        "version_number": 1
      },
      "updated_at": "2024-03-07T19:53:46.404970+00:00"
    },
    {
      "agency": "US-XYZ",
      "category": "discretionary",
      "category_explanation": null,
      "created_at": "2024-03-07T19:53:46.508790+00:00",
      "opportunity_assistance_listings": [
        {
          "assistance_listing_number": "24.109",
          "program_title": "Miller-Johnson"
        }
      ],
      "opportunity_id": 14,
      "opportunity_number": "ABC-14-XYZ-001",
      "opportunity_status": "closed",
      "opportunity_title": "Research into Production assistant, television industry",
      "summary": {
        "additional_info_url": "grants.gov",
        "additional_info_url_description": "Click me for additional info",
        "agency_code": "US-XYZ",
        "agency_contact_description": "For more information contact us at - Away opportunity though support health someone. Home so occur term eight trial month. Lot require police cut market toward drive.",
        "agency_email_address": "areeves@example.org",
        "agency_email_address_description": "Contact US Xylophone Yak Zoo via email",
        "agency_name": "US Xylophone Yak Zoo",
        "agency_phone_number": "123-456-0013",
        "applicant_eligibility_description": null,
        "applicant_types": [
          "individuals",
          "small_businesses",
          "for_profit_organizations_other_than_small_businesses"
        ],
        "archive_date": "2024-04-03",
        "award_ceiling": 2165000,
        "award_floor": 103095,
        "close_date": "2024-02-21",
        "close_date_description": "Key generation since staff.",
        "estimated_total_program_funding": 2165000,
        "expected_number_of_awards": 21,
        "fiscal_year": null,
        "forecasted_award_date": null,
        "forecasted_close_date": null,
        "forecasted_close_date_description": null,
        "forecasted_post_date": null,
        "forecasted_project_start_date": null,
        "funding_categories": ["affordable_care_act"],
        "funding_category_description": null,
        "funding_instruments": ["procurement_contract", "grant", "other"],
        "is_cost_sharing": true,
        "is_forecast": false,
        "post_date": "2024-01-31",
        "summary_description": "Example summary - Partner never guy. Sit ready too cause situation least month. Over suggest here.",
        "version_number": 1
      },
      "updated_at": "2024-03-07T19:53:46.508790+00:00"
    },
    {
      "agency": "US-123",
      "category": "mandatory",
      "category_explanation": null,
      "created_at": "2024-03-07T19:53:46.584556+00:00",
      "opportunity_assistance_listings": [
        {
          "assistance_listing_number": "24.586",
          "program_title": "Foster-Galvan"
        }
      ],
      "opportunity_id": 15,
      "opportunity_number": "ABC-15-XYZ-001",
      "opportunity_status": "closed",
      "opportunity_title": "Research into Environmental education officer industry",
      "summary": {
        "additional_info_url": "google.com",
        "additional_info_url_description": "Click me for additional info",
        "agency_code": "US-123",
        "agency_contact_description": "For more information contact us at - Find win easy drug. Among free fact bar even start speak.",
        "agency_email_address": "woodphilip@example.com",
        "agency_email_address_description": "Contact US Number Department via email",
        "agency_name": "US Number Department",
        "agency_phone_number": "123-456-0014",
        "applicant_eligibility_description": "List need PM worry site issue begin. Include others necessary form minute miss moment degree. Teach forward think compare cell. Maintain half medical many hope. Quite authority enough pass fine spend. Coach future attorney degree effort sound north.",
        "applicant_types": ["state_governments", "unrestricted", "other"],
        "archive_date": "2024-04-02",
        "award_ceiling": 955000,
        "award_floor": 47750,
        "close_date": "2024-02-25",
        "close_date_description": "Their institution generation door wide chair recently believe.",
        "estimated_total_program_funding": 955000,
        "expected_number_of_awards": 20,
        "fiscal_year": null,
        "forecasted_award_date": null,
        "forecasted_close_date": null,
        "forecasted_close_date_description": null,
        "forecasted_post_date": null,
        "forecasted_project_start_date": null,
        "funding_categories": ["agriculture", "recovery_act", "other"],
        "funding_category_description": "Challenge run develop leader life fund begin.",
        "funding_instruments": [
          "procurement_contract",
          "grant",
          "cooperative_agreement"
        ],
        "is_cost_sharing": true,
        "is_forecast": false,
        "post_date": "2024-01-26",
        "summary_description": "Example summary - Product keep team music whom explain. Today dark every suddenly line increase.",
        "version_number": 1
      },
      "updated_at": "2024-03-07T19:53:46.584556+00:00"
    },
    {
      "agency": "US-ABC",
      "category": "other",
      "category_explanation": "Category as chosen by order #255",
      "created_at": "2024-03-07T19:53:46.688444+00:00",
      "opportunity_assistance_listings": [
        {
          "assistance_listing_number": "31.810",
          "program_title": "Dillon, Bell and Meadows"
        },
        {
          "assistance_listing_number": "34.195",
          "program_title": "Ingram, Thomas and Finley"
        },
        {
          "assistance_listing_number": "88.528",
          "program_title": "Morgan-Carey"
        }
      ],
      "opportunity_id": 16,
      "opportunity_number": "ABC-16-XYZ-001",
      "opportunity_status": "archived",
      "opportunity_title": "Research into Scientist, clinical (histocompatibility and immunogenetics) industry",
      "summary": {
        "additional_info_url": "grants.gov",
        "additional_info_url_description": "Click me for additional info",
        "agency_code": "US-ABC",
        "agency_contact_description": "For more information contact us at - Work eye he gun. Now lead later commercial through.",
        "agency_email_address": "andersontimothy@example.org",
        "agency_email_address_description": "Contact US Alphabetical Basic Corp via email",
        "agency_name": "US Alphabetical Basic Corp",
        "agency_phone_number": "123-456-0015",
        "applicant_eligibility_description": null,
        "applicant_types": ["county_governments"],
        "archive_date": "2024-02-28",
        "award_ceiling": 1670000,
        "award_floor": 278333,
        "close_date": "2024-02-19",
        "close_date_description": "Idea reality half.",
        "estimated_total_program_funding": 1670000,
        "expected_number_of_awards": 6,
        "fiscal_year": null,
        "forecasted_award_date": null,
        "forecasted_close_date": null,
        "forecasted_close_date_description": null,
        "forecasted_post_date": null,
        "forecasted_project_start_date": null,
        "funding_categories": ["arts", "business_and_commerce"],
        "funding_category_description": "Indeed culture way determine appear.",
        "funding_instruments": ["other", "cooperative_agreement"],
        "is_cost_sharing": false,
        "is_forecast": false,
        "post_date": "2024-01-27",
        "summary_description": "Example summary - Happen some large guess. Oil send debate.",
        "version_number": 1
      },
      "updated_at": "2024-03-07T19:53:46.688444+00:00"
    },
    {
      "agency": "US-XYZ",
      "category": "mandatory",
      "category_explanation": null,
      "created_at": "2024-03-07T19:53:46.775641+00:00",
      "opportunity_assistance_listings": [
        {
          "assistance_listing_number": "44.517",
          "program_title": "Freeman-Guzman"
        },
        {
          "assistance_listing_number": "30.723",
          "program_title": "Taylor-Walton"
        },
        {
          "assistance_listing_number": "31.500",
          "program_title": "Walter-Buck"
        }
      ],
      "opportunity_id": 17,
      "opportunity_number": "ABC-17-XYZ-001",
      "opportunity_status": "archived",
      "opportunity_title": "Research into Therapist, music industry",
      "summary": {
        "additional_info_url": "google.com",
        "additional_info_url_description": "Click me for additional info",
        "agency_code": "US-XYZ",
        "agency_contact_description": "For more information contact us at - When think blood after nor reveal experience. Forget action nothing table simple already. Billion pick us machine.",
        "agency_email_address": "fmiller@example.com",
        "agency_email_address_description": "Contact US Xylophone Yak Zoo via email",
        "agency_name": "US Xylophone Yak Zoo",
        "agency_phone_number": "123-456-0016",
        "applicant_eligibility_description": "Guy sell war past spend work at. Live structure place industry executive book. Pull different camera article.",
        "applicant_types": [
          "city_or_township_governments",
          "special_district_governments"
        ],
        "archive_date": "2024-02-25",
        "award_ceiling": 2475000,
        "award_floor": 495000,
        "close_date": "2024-02-19",
        "close_date_description": "Situation glass history street medical.",
        "estimated_total_program_funding": 2475000,
        "expected_number_of_awards": 5,
        "fiscal_year": null,
        "forecasted_award_date": null,
        "forecasted_close_date": null,
        "forecasted_close_date_description": null,
        "forecasted_post_date": null,
        "forecasted_project_start_date": null,
        "funding_categories": ["community_development"],
        "funding_category_description": null,
        "funding_instruments": ["procurement_contract", "grant"],
        "is_cost_sharing": false,
        "is_forecast": false,
        "post_date": "2024-01-29",
        "summary_description": "Example summary - Purpose reflect wide if sign sit name.",
        "version_number": 1
      },
      "updated_at": "2024-03-07T19:53:46.775641+00:00"
    },
    {
      "agency": "US-123",
      "category": "discretionary",
      "category_explanation": null,
      "created_at": "2024-03-07T19:53:46.858133+00:00",
      "opportunity_assistance_listings": [
        {
          "assistance_listing_number": "60.048",
          "program_title": "Marshall-Moore"
        },
        {
          "assistance_listing_number": "31.913",
          "program_title": "Cohen-Russell"
        },
        {
          "assistance_listing_number": "54.678",
          "program_title": "Decker-Mullen"
        }
      ],
      "opportunity_id": 18,
      "opportunity_number": "ABC-18-XYZ-001",
      "opportunity_status": "archived",
      "opportunity_title": "Research into Horticultural consultant industry",
      "summary": {
        "additional_info_url": "grants.gov",
        "additional_info_url_description": "Click me for additional info",
        "agency_code": "US-123",
        "agency_contact_description": "For more information contact us at - Capital however music room fast though.",
        "agency_email_address": "davidgrant@example.net",
        "agency_email_address_description": "Contact US Number Department via email",
        "agency_name": "US Number Department",
        "agency_phone_number": "123-456-0017",
        "applicant_eligibility_description": null,
        "applicant_types": [
          "public_and_state_institutions_of_higher_education",
          "independent_school_districts"
        ],
        "archive_date": "2024-02-27",
        "award_ceiling": 6990000,
        "award_floor": 582500,
        "close_date": "2024-02-20",
        "close_date_description": "Point difference within.",
        "estimated_total_program_funding": 6990000,
        "expected_number_of_awards": 12,
        "fiscal_year": null,
        "forecasted_award_date": null,
        "forecasted_close_date": null,
        "forecasted_close_date_description": null,
        "forecasted_post_date": null,
        "forecasted_project_start_date": null,
        "funding_categories": [
          "disaster_prevention_and_relief",
          "consumer_protection"
        ],
        "funding_category_description": "Lose paper skill receive three.",
        "funding_instruments": ["other", "cooperative_agreement"],
        "is_cost_sharing": true,
        "is_forecast": false,
        "post_date": "2024-01-27",
        "summary_description": "Example summary - Process work let hotel fast month throughout. Difficult music often whether song. Generation responsibility tax produce sister answer. Keep only laugh new.",
        "version_number": 1
      },
      "updated_at": "2024-03-07T19:53:46.858133+00:00"
    },
    {
      "agency": "US-ABC",
      "category": "other",
      "category_explanation": "Category as chosen by order #360",
      "created_at": "2024-03-07T19:53:46.970202+00:00",
      "opportunity_assistance_listings": [
        {
          "assistance_listing_number": "58.681",
          "program_title": "Coleman, Wade and Keller"
        },
        {
          "assistance_listing_number": "69.724",
          "program_title": "Gordon Inc"
        },
        {
          "assistance_listing_number": "94.830",
          "program_title": "Anthony-Young"
        }
      ],
      "opportunity_id": 19,
      "opportunity_number": "ABC-19-XYZ-001",
      "opportunity_status": "archived",
      "opportunity_title": "Research into Freight forwarder industry",
      "summary": {
        "additional_info_url": "google.com",
        "additional_info_url_description": "Click me for additional info",
        "agency_code": "US-ABC",
        "agency_contact_description": "For more information contact us at - Set draw test. Challenge though year. Executive support across generation leg back.",
        "agency_email_address": "floresdebra@example.org",
        "agency_email_address_description": "Contact US Alphabetical Basic Corp via email",
        "agency_name": "US Alphabetical Basic Corp",
        "agency_phone_number": "123-456-0018",
        "applicant_eligibility_description": "Time collection state action key. Trade hard table statement eye marriage report threat. Today interview toward senior establish south. Would performance statement safe once ever.",
        "applicant_types": ["private_institutions_of_higher_education"],
        "archive_date": "2024-02-27",
        "award_ceiling": 7410000,
        "award_floor": 1482000,
        "close_date": "2024-02-19",
        "close_date_description": "On sport though business.",
        "estimated_total_program_funding": 7410000,
        "expected_number_of_awards": 5,
        "fiscal_year": null,
        "forecasted_award_date": null,
        "forecasted_close_date": null,
        "forecasted_close_date_description": null,
        "forecasted_post_date": null,
        "forecasted_project_start_date": null,
        "funding_categories": [
          "education",
          "energy",
          "employment_labor_and_training"
        ],
        "funding_category_description": "Me stop letter would huge.",
        "funding_instruments": ["procurement_contract", "grant"],
        "is_cost_sharing": true,
        "is_forecast": false,
        "post_date": "2024-01-30",
        "summary_description": "Example summary - Present soldier do camera. Lawyer cost bar product sell. Director message order project customer total dark.",
        "version_number": 1
      },
      "updated_at": "2024-03-07T19:53:46.970202+00:00"
    },
    {
      "agency": "US-XYZ",
      "category": "earmark",
      "category_explanation": null,
      "created_at": "2024-03-07T19:53:47.083952+00:00",
      "opportunity_assistance_listings": [
        {
          "assistance_listing_number": "21.741",
          "program_title": "Ramos, Jordan and Simmons"
        },
        {
          "assistance_listing_number": "10.260",
          "program_title": "Fry and Sons"
        }
      ],
      "opportunity_id": 20,
      "opportunity_number": "ABC-20-XYZ-001",
      "opportunity_status": "archived",
      "opportunity_title": "Research into Therapist, speech and language industry",
      "summary": {
        "additional_info_url": "grants.gov",
        "additional_info_url_description": "Click me for additional info",
        "agency_code": "US-XYZ",
        "agency_contact_description": "For more information contact us at - Research surface watch likely anyone quite cup. Outside often store student loss spend just. Us suggest them couple.",
        "agency_email_address": "torresedward@example.net",
        "agency_email_address_description": "Contact US Xylophone Yak Zoo via email",
        "agency_name": "US Xylophone Yak Zoo",
        "agency_phone_number": "123-456-0019",
        "applicant_eligibility_description": null,
        "applicant_types": [
          "federally_recognized_native_american_tribal_governments"
        ],
        "archive_date": "2024-02-27",
        "award_ceiling": 9175000,
        "award_floor": 1835000,
        "close_date": "2024-02-19",
        "close_date_description": "Accept father policy crime cause have.",
        "estimated_total_program_funding": 9175000,
        "expected_number_of_awards": 5,
        "fiscal_year": null,
        "forecasted_award_date": null,
        "forecasted_close_date": null,
        "forecasted_close_date_description": null,
        "forecasted_post_date": null,
        "forecasted_project_start_date": null,
        "funding_categories": ["health", "food_and_nutrition", "environment"],
        "funding_category_description": null,
        "funding_instruments": ["grant", "other", "cooperative_agreement"],
        "is_cost_sharing": true,
        "is_forecast": false,
        "post_date": "2024-01-29",
        "summary_description": "Example summary - Worry not contain health ago on. With return eat poor consider wish forward.",
        "version_number": 1
      },
      "updated_at": "2024-03-07T19:53:47.083952+00:00"
    },
    {
      "agency": "US-123",
      "category": "discretionary",
      "category_explanation": null,
      "created_at": "2024-03-07T19:53:47.198722+00:00",
      "opportunity_assistance_listings": [
        {
          "assistance_listing_number": "47.640",
          "program_title": "Richards Inc"
        },
        {
          "assistance_listing_number": "79.806",
          "program_title": "Odonnell-Garcia"
        }
      ],
      "opportunity_id": 21,
      "opportunity_number": "ABC-21-XYZ-001",
      "opportunity_status": "archived",
      "opportunity_title": "Research into Theatre manager industry",
      "summary": {
        "additional_info_url": "google.com",
        "additional_info_url_description": "Click me for additional info",
        "agency_code": "US-123",
        "agency_contact_description": "For more information contact us at - Public than nice another serious face. By participant executive arrive back national must.",
        "agency_email_address": "ramosdavid@example.org",
        "agency_email_address_description": "Contact US Number Department via email",
        "agency_name": "US Number Department",
        "agency_phone_number": "123-456-0020",
        "applicant_eligibility_description": null,
        "applicant_types": ["other_native_american_tribal_organizations"],
        "archive_date": "2024-02-23",
        "award_ceiling": 9150000,
        "award_floor": 915000,
        "close_date": null,
        "close_date_description": null,
        "estimated_total_program_funding": 9150000,
        "expected_number_of_awards": 10,
        "fiscal_year": 2024,
        "forecasted_award_date": "2024-09-19",
        "forecasted_close_date": "2024-05-11",
        "forecasted_close_date_description": "Draw central generation term ability eye some.",
        "forecasted_post_date": "2024-03-25",
        "forecasted_project_start_date": "2024-11-09",
        "funding_categories": ["humanities", "housing"],
        "funding_category_description": "Season meeting effect sound help.",
        "funding_instruments": ["procurement_contract"],
        "is_cost_sharing": true,
        "is_forecast": true,
        "post_date": "2024-01-27",
        "summary_description": "Example summary - Or society Republican usually.",
        "version_number": 1
      },
      "updated_at": "2024-03-07T19:53:47.198722+00:00"
    },
    {
      "agency": "US-ABC",
      "category": "discretionary",
      "category_explanation": null,
      "created_at": "2024-03-07T19:53:47.286933+00:00",
      "opportunity_assistance_listings": [
        {
          "assistance_listing_number": "43.967",
          "program_title": "Austin-Freeman"
        }
      ],
      "opportunity_id": 22,
      "opportunity_number": "ABC-22-XYZ-001",
      "opportunity_status": "archived",
      "opportunity_title": "Research into Air traffic controller industry",
      "summary": {
        "additional_info_url": "grants.gov",
        "additional_info_url_description": "Click me for additional info",
        "agency_code": "US-ABC",
        "agency_contact_description": "For more information contact us at - Positive care perform send class body. Computer care what suggest traditional coach coach. Will begin prevent majority.",
        "agency_email_address": "kristin43@example.com",
        "agency_email_address_description": "Contact US Alphabetical Basic Corp via email",
        "agency_name": "US Alphabetical Basic Corp",
        "agency_phone_number": "123-456-0021",
        "applicant_eligibility_description": null,
        "applicant_types": ["public_and_indian_housing_authorities"],
        "archive_date": "2024-02-22",
        "award_ceiling": 2165000,
        "award_floor": 98409,
        "close_date": null,
        "close_date_description": null,
        "estimated_total_program_funding": 2165000,
        "expected_number_of_awards": 22,
        "fiscal_year": 2025,
        "forecasted_award_date": "2024-09-23",
        "forecasted_close_date": "2024-04-24",
        "forecasted_close_date_description": "Ago a environment.",
        "forecasted_post_date": "2024-03-22",
        "forecasted_project_start_date": "2025-02-07",
        "funding_categories": ["infrastructure_investment_and_jobs_act"],
        "funding_category_description": null,
        "funding_instruments": ["grant", "other", "cooperative_agreement"],
        "is_cost_sharing": true,
        "is_forecast": true,
        "post_date": "2024-01-28",
        "summary_description": "Example summary - Edge although task control. Issue unit in fish organization off.",
        "version_number": 1
      },
      "updated_at": "2024-03-07T19:53:47.286933+00:00"
    },
    {
      "agency": "US-XYZ",
      "category": "discretionary",
      "category_explanation": null,
      "created_at": "2024-03-07T19:53:47.374837+00:00",
      "opportunity_assistance_listings": [
        {
          "assistance_listing_number": "62.646",
          "program_title": "Tanner, Hayes and Vasquez"
        }
      ],
      "opportunity_id": 23,
      "opportunity_number": "ABC-23-XYZ-001",
      "opportunity_status": "archived",
      "opportunity_title": "Research into Archivist industry",
      "summary": {
        "additional_info_url": "google.com",
        "additional_info_url_description": "Click me for additional info",
        "agency_code": "US-XYZ",
        "agency_contact_description": "For more information contact us at - Physical end fact baby increase last about. Of try game thing image.",
        "agency_email_address": "roachalejandra@example.net",
        "agency_email_address_description": "Contact US Xylophone Yak Zoo via email",
        "agency_name": "US Xylophone Yak Zoo",
        "agency_phone_number": "123-456-0022",
        "applicant_eligibility_description": null,
        "applicant_types": ["nonprofits_non_higher_education_with_501c3"],
        "archive_date": "2024-02-25",
        "award_ceiling": 9305000,
        "award_floor": 516944,
        "close_date": null,
        "close_date_description": null,
        "estimated_total_program_funding": 9305000,
        "expected_number_of_awards": 18,
        "fiscal_year": 2025,
        "forecasted_award_date": "2024-09-08",
        "forecasted_close_date": "2024-04-26",
        "forecasted_close_date_description": "Establish available represent experience subject alone window.",
        "forecasted_post_date": "2024-03-24",
        "forecasted_project_start_date": "2025-01-25",
        "funding_categories": ["information_and_statistics"],
        "funding_category_description": null,
        "funding_instruments": ["procurement_contract"],
        "is_cost_sharing": false,
        "is_forecast": true,
        "post_date": "2024-01-30",
        "summary_description": "Example summary - Impact laugh they head plan. Local structure front these.",
        "version_number": 1
      },
      "updated_at": "2024-03-07T19:53:47.374837+00:00"
    },
    {
      "agency": "US-123",
      "category": "mandatory",
      "category_explanation": null,
      "created_at": "2024-03-07T19:53:47.418052+00:00",
      "opportunity_assistance_listings": [
        {
          "assistance_listing_number": "47.876",
          "program_title": "Watson PLC"
        },
        {
          "assistance_listing_number": "13.351",
          "program_title": "Shea Ltd"
        }
      ],
      "opportunity_id": 24,
      "opportunity_number": "ABC-24-XYZ-001",
      "opportunity_status": "archived",
      "opportunity_title": "Research into Financial trader industry",
      "summary": {
        "additional_info_url": "grants.gov",
        "additional_info_url_description": "Click me for additional info",
        "agency_code": "US-123",
        "agency_contact_description": "For more information contact us at - Drop former dark first value next. White between read.",
        "agency_email_address": "andrew43@example.net",
        "agency_email_address_description": "Contact US Number Department via email",
        "agency_name": "US Number Department",
        "agency_phone_number": "123-456-0023",
        "applicant_eligibility_description": "Movie change my quite her agree. Television artist professional kid realize who. Radio bar finally decide. School ground outside blood item upon race world.",
        "applicant_types": ["nonprofits_non_higher_education_without_501c3"],
        "archive_date": "2024-02-26",
        "award_ceiling": 8385000,
        "award_floor": 381136,
        "close_date": null,
        "close_date_description": null,
        "estimated_total_program_funding": 8385000,
        "expected_number_of_awards": 22,
        "fiscal_year": 2024,
        "forecasted_award_date": "2024-09-05",
        "forecasted_close_date": "2024-05-18",
        "forecasted_close_date_description": "Get dark let possible authority all well.",
        "forecasted_post_date": "2024-03-26",
        "forecasted_project_start_date": "2024-12-30",
        "funding_categories": [
          "law_justice_and_legal_services",
          "income_security_and_social_services",
          "natural_resources"
        ],
        "funding_category_description": "Though city commercial believe market middle half.",
        "funding_instruments": ["grant", "other", "cooperative_agreement"],
        "is_cost_sharing": false,
        "is_forecast": true,
        "post_date": "2024-01-28",
        "summary_description": "Example summary - Day gun subject whether. Rate ability goal. Person mission tonight more per capital arm.",
        "version_number": 1
      },
      "updated_at": "2024-03-07T19:53:47.418052+00:00"
    },
    {
      "agency": "US-ABC",
      "category": "other",
      "category_explanation": "Category as chosen by order #624",
      "created_at": "2024-03-07T19:53:47.491071+00:00",
      "opportunity_assistance_listings": [
        {
          "assistance_listing_number": "30.756",
          "program_title": "Harris, Forbes and Price"
        },
        {
          "assistance_listing_number": "97.159",
          "program_title": "Smith-Anderson"
        }
      ],
      "opportunity_id": 25,
      "opportunity_number": "ABC-25-XYZ-001",
      "opportunity_status": "archived",
      "opportunity_title": "Research into Lexicographer industry",
      "summary": {
        "additional_info_url": "google.com",
        "additional_info_url_description": "Click me for additional info",
        "agency_code": "US-ABC",
        "agency_contact_description": "For more information contact us at - Answer leg appear memory. Feel west glass difficult threat nor. Product politics enjoy involve.",
        "agency_email_address": "omar23@example.net",
        "agency_email_address_description": "Contact US Alphabetical Basic Corp via email",
        "agency_name": "US Alphabetical Basic Corp",
        "agency_phone_number": "123-456-0024",
        "applicant_eligibility_description": "Truth whether sell work leave spring few. Simple conference stay say floor ten be my. Camera should down. Pm draw concern. Accept situation century purpose the decide than.",
        "applicant_types": [
          "individuals",
          "for_profit_organizations_other_than_small_businesses"
        ],
        "archive_date": "2024-02-28",
        "award_ceiling": 7290000,
        "award_floor": 607500,
        "close_date": null,
        "close_date_description": null,
        "estimated_total_program_funding": 7290000,
        "expected_number_of_awards": 12,
        "fiscal_year": 2024,
        "forecasted_award_date": "2024-09-29",
        "forecasted_close_date": "2024-04-20",
        "forecasted_close_date_description": "Include sense treatment idea.",
        "forecasted_post_date": "2024-03-23",
        "forecasted_project_start_date": "2024-11-12",
        "funding_categories": ["opportunity_zone_benefits"],
        "funding_category_description": null,
        "funding_instruments": ["procurement_contract"],
        "is_cost_sharing": true,
        "is_forecast": true,
        "post_date": "2024-01-26",
        "summary_description": "Example summary - Scientist industry sense lay type beat. Option doctor present public country picture black. Surface base exactly begin money part.",
        "version_number": 1
      },
      "updated_at": "2024-03-07T19:53:47.491071+00:00"
    },
    {
      "agency": null,
      "category": null,
      "category_explanation": null,
      "created_at": "2024-03-07T19:53:47.631094+00:00",
      "opportunity_assistance_listings": [],
      "opportunity_id": 31,
      "opportunity_number": "ABC-31-XYZ-001",
      "opportunity_status": "posted",
      "opportunity_title": "Research into Engineering geologist industry",
      "summary": {
        "additional_info_url": null,
        "additional_info_url_description": null,
        "agency_code": null,
        "agency_contact_description": null,
        "agency_email_address": null,
        "agency_email_address_description": null,
        "agency_name": null,
        "agency_phone_number": null,
        "applicant_eligibility_description": null,
        "applicant_types": [],
        "archive_date": null,
        "award_ceiling": null,
        "award_floor": null,
        "close_date": null,
        "close_date_description": null,
        "estimated_total_program_funding": null,
        "expected_number_of_awards": null,
        "fiscal_year": null,
        "forecasted_award_date": null,
        "forecasted_close_date": null,
        "forecasted_close_date_description": null,
        "forecasted_post_date": null,
        "forecasted_project_start_date": null,
        "funding_categories": [],
        "funding_category_description": null,
        "funding_instruments": [],
        "is_cost_sharing": null,
        "is_forecast": false,
        "post_date": null,
        "summary_description": null,
        "version_number": 1
      },
      "updated_at": "2024-03-07T19:53:47.631094+00:00"
    },
    {
      "agency": null,
      "category": null,
      "category_explanation": null,
      "created_at": "2024-03-07T19:53:47.637768+00:00",
      "opportunity_assistance_listings": [],
      "opportunity_id": 32,
      "opportunity_number": "ABC-32-XYZ-001",
      "opportunity_status": "posted",
      "opportunity_title": "Research into Financial planner industry",
      "summary": {
        "additional_info_url": null,
        "additional_info_url_description": null,
        "agency_code": null,
        "agency_contact_description": null,
        "agency_email_address": null,
        "agency_email_address_description": null,
        "agency_name": null,
        "agency_phone_number": null,
        "applicant_eligibility_description": null,
        "applicant_types": [],
        "archive_date": null,
        "award_ceiling": null,
        "award_floor": null,
        "close_date": null,
        "close_date_description": null,
        "estimated_total_program_funding": null,
        "expected_number_of_awards": null,
        "fiscal_year": null,
        "forecasted_award_date": null,
        "forecasted_close_date": null,
        "forecasted_close_date_description": null,
        "forecasted_post_date": null,
        "forecasted_project_start_date": null,
        "funding_categories": [],
        "funding_category_description": null,
        "funding_instruments": [],
        "is_cost_sharing": null,
        "is_forecast": false,
        "post_date": null,
        "summary_description": null,
        "version_number": 1
      },
      "updated_at": "2024-03-07T19:53:47.637768+00:00"
    },
    {
      "agency": null,
      "category": null,
      "category_explanation": null,
      "created_at": "2024-03-07T19:53:47.646047+00:00",
      "opportunity_assistance_listings": [],
      "opportunity_id": 33,
      "opportunity_number": "ABC-33-XYZ-001",
      "opportunity_status": "posted",
      "opportunity_title": "Research into Engineer, manufacturing industry",
      "summary": {
        "additional_info_url": null,
        "additional_info_url_description": null,
        "agency_code": null,
        "agency_contact_description": null,
        "agency_email_address": null,
        "agency_email_address_description": null,
        "agency_name": null,
        "agency_phone_number": null,
        "applicant_eligibility_description": null,
        "applicant_types": [],
        "archive_date": null,
        "award_ceiling": null,
        "award_floor": null,
        "close_date": null,
        "close_date_description": null,
        "estimated_total_program_funding": null,
        "expected_number_of_awards": null,
        "fiscal_year": null,
        "forecasted_award_date": null,
        "forecasted_close_date": null,
        "forecasted_close_date_description": null,
        "forecasted_post_date": null,
        "forecasted_project_start_date": null,
        "funding_categories": [],
        "funding_category_description": null,
        "funding_instruments": [],
        "is_cost_sharing": null,
        "is_forecast": false,
        "post_date": null,
        "summary_description": null,
        "version_number": 1
      },
      "updated_at": "2024-03-07T19:53:47.646047+00:00"
    },
    {
      "agency": null,
      "category": null,
      "category_explanation": null,
      "created_at": "2024-03-07T19:53:47.652396+00:00",
      "opportunity_assistance_listings": [],
      "opportunity_id": 34,
      "opportunity_number": "ABC-34-XYZ-001",
      "opportunity_status": "posted",
      "opportunity_title": "Research into Therapist, art industry",
      "summary": {
        "additional_info_url": null,
        "additional_info_url_description": null,
        "agency_code": null,
        "agency_contact_description": null,
        "agency_email_address": null,
        "agency_email_address_description": null,
        "agency_name": null,
        "agency_phone_number": null,
        "applicant_eligibility_description": null,
        "applicant_types": [],
        "archive_date": null,
        "award_ceiling": null,
        "award_floor": null,
        "close_date": null,
        "close_date_description": null,
        "estimated_total_program_funding": null,
        "expected_number_of_awards": null,
        "fiscal_year": null,
        "forecasted_award_date": null,
        "forecasted_close_date": null,
        "forecasted_close_date_description": null,
        "forecasted_post_date": null,
        "forecasted_project_start_date": null,
        "funding_categories": [],
        "funding_category_description": null,
        "funding_instruments": [],
        "is_cost_sharing": null,
        "is_forecast": false,
        "post_date": null,
        "summary_description": null,
        "version_number": 1
      },
      "updated_at": "2024-03-07T19:53:47.652396+00:00"
    },
    {
      "agency": null,
      "category": null,
      "category_explanation": null,
      "created_at": "2024-03-07T19:53:47.663557+00:00",
      "opportunity_assistance_listings": [],
      "opportunity_id": 35,
      "opportunity_number": "ABC-35-XYZ-001",
      "opportunity_status": "posted",
      "opportunity_title": "Research into Catering manager industry",
      "summary": {
        "additional_info_url": null,
        "additional_info_url_description": null,
        "agency_code": null,
        "agency_contact_description": null,
        "agency_email_address": null,
        "agency_email_address_description": null,
        "agency_name": null,
        "agency_phone_number": null,
        "applicant_eligibility_description": null,
        "applicant_types": [],
        "archive_date": null,
        "award_ceiling": null,
        "award_floor": null,
        "close_date": null,
        "close_date_description": null,
        "estimated_total_program_funding": null,
        "expected_number_of_awards": null,
        "fiscal_year": null,
        "forecasted_award_date": null,
        "forecasted_close_date": null,
        "forecasted_close_date_description": null,
        "forecasted_post_date": null,
        "forecasted_project_start_date": null,
        "funding_categories": [],
        "funding_category_description": null,
        "funding_instruments": [],
        "is_cost_sharing": null,
        "is_forecast": false,
        "post_date": null,
        "summary_description": null,
        "version_number": 1
      },
      "updated_at": "2024-03-07T19:53:47.663557+00:00"
    }
  ],
  "message": "Success",
  "pagination_info": {
    "order_by": "opportunity_id",
    "page_offset": 1,
    "page_size": 30,
    "sort_direction": "ascending",
    "total_pages": 2,
    "total_records": 60
  },
  "status_code": 200,
  "warnings": []
}
